{
    "info": {
        "description": "ISAT",
        "folder": "E:/2026Project/RMYC_Simulator_VisionData_26_3_22/label_toolkit/origin_pics",
        "name": "2026_03_22_11_05_56_001542.jpg",
        "width": 1280,
        "height": 720,
        "depth": 3,
        "note": ""
    },
    "objects": [
        {
            "category": "big_column",
            "group": 1,
            "segmentation": [
                [
                    1047.0,
                    0.1
                ],
                [
                    987.0,
                    70.0
                ],
                [
                    975.0,
                    238.0
                ],
                [
                    974.0,
                    296.0
                ],
                [
                    970.0,
                    320.0
                ],
                [
                    965.0,
                    395.0
                ],
                [
                    966.0,
                    427.0
                ],
                [
                    972.0,
                    436.0
                ],
                [
                    981.0,
                    443.0
                ],
                [
                    982.0,
                    447.0
                ],
                [
                    1000.0,
                    464.0
                ],
                [
                    1002.0,
                    469.0
                ],
                [
                    1020.0,
                    486.0
                ],
                [
                    1022.0,
                    491.0
                ],
                [
                    1041.0,
                    509.0
                ],
                [
                    1042.0,
                    513.0
                ],
                [
                    1056.0,
                    524.0
                ],
                [
                    1062.0,
                    534.0
                ],
                [
                    1083.0,
                    555.0
                ],
                [
                    1279.0,
                    570.0
                ],
                [
                    1279.0,
                    0.1
                ]
            ],
            "area": 160972.3,
            "layer": 1.0,
            "bbox": [
                964.5002439619565,
                -0.6050621253630992,
                1279.5,
                570.4985421670551
            ],
            "iscrowd": false,
            "note": ""
        }
    ]
}